odoo/addons/l10n_es_pos/README.rst
odoo/addons/l10n_es_pos/__init__.py
odoo/addons/l10n_es_pos/__manifest__.py
odoo/addons/l10n_es_pos/hooks.py
odoo/addons/l10n_es_pos/i18n/ca.po
odoo/addons/l10n_es_pos/i18n/es.po
odoo/addons/l10n_es_pos/i18n/l10n_es_pos.pot
odoo/addons/l10n_es_pos/migrations/11.0.1.0.0/post-migrate.py
odoo/addons/l10n_es_pos/migrations/11.0.2.0.0/pre-migration.py
odoo/addons/l10n_es_pos/models/__init__.py
odoo/addons/l10n_es_pos/models/ir_sequence.py
odoo/addons/l10n_es_pos/models/pos_config.py
odoo/addons/l10n_es_pos/models/pos_order.py
odoo/addons/l10n_es_pos/static/description/icon.png
odoo/addons/l10n_es_pos/static/src/js/models.js
odoo/addons/l10n_es_pos/static/src/js/screens.js
odoo/addons/l10n_es_pos/static/src/xml/pos.xml
odoo/addons/l10n_es_pos/views/pos_templates.xml
odoo/addons/l10n_es_pos/views/pos_views.xml
odoo11_addon_l10n_es_pos-11.0.3.0.3.dist-info/METADATA
odoo11_addon_l10n_es_pos-11.0.3.0.3.dist-info/WHEEL
odoo11_addon_l10n_es_pos-11.0.3.0.3.dist-info/top_level.txt
odoo11_addon_l10n_es_pos-11.0.3.0.3.dist-info/RECORD
